{
  "minecraft:adventure/adventuring_time": {
    "criteria": {
      "minecraft:taiga": "2025-04-24 19:12:28 -0500",
      "minecraft:river": "2025-04-24 19:11:25 -0500",
      "minecraft:lush_caves": "2025-04-24 19:22:01 -0500",
      "minecraft:deep_cold_ocean": "2025-04-25 16:26:38 -0500"
    },
    "done": false
  },
  "minecraft:story/root": {
    "criteria": {
      "crafting_table": "2025-04-24 19:39:10 -0500"
    },
    "done": true
  },
  "cold_sweat:recipes/goat_armor": {
    "criteria": {
      "has_legs_recipe": "2025-04-25 15:36:42 -0500"
    },
    "done": true
  },
  "cold_sweat:recipes/thermolith": {
    "criteria": {
      "has_recipe": "2025-04-25 15:36:42 -0500"
    },
    "done": true
  },
  "cold_sweat:recipes/hoglin_armor": {
    "criteria": {
      "has_legs_recipe": "2025-04-25 15:36:42 -0500"
    },
    "done": true
  },
  "cold_sweat:recipes/soulspring_lamp": {
    "criteria": {
      "has_recipe": "2025-04-25 15:36:42 -0500"
    },
    "done": true
  },
  "cold_sweat:recipes/waterskin": {
    "criteria": {
      "has_recipe": "2025-04-25 15:36:42 -0500"
    },
    "done": true
  },
  "cold_sweat:recipes/thermometer": {
    "criteria": {
      "has_recipe": "2025-04-25 15:36:42 -0500"
    },
    "done": true
  },
  "takesapillage:root": {
    "criteria": {
      "always": "2025-04-25 15:36:44 -0500"
    },
    "done": true
  },
  "lootr:root": {
    "criteria": {
      "always_true": "2025-04-25 15:36:44 -0500"
    },
    "done": true
  },
  "health_and_disease:grant_book_on_first_join": {
    "criteria": {
      "tick": "2025-04-25 15:36:44 -0500"
    },
    "done": true
  },
  "cold_sweat:huddle_close": {
    "criteria": {
      "requirement": "2025-04-25 15:36:44 -0500"
    },
    "done": true
  },
  "parcool:grant_parcool_guide": {
    "criteria": {
      "tick": "2025-04-25 15:36:44 -0500"
    },
    "done": true
  },
  "cold_sweat:root": {
    "criteria": {
      "requirement": "2025-04-25 15:36:44 -0500"
    },
    "done": true
  },
  "walkietalkie:walkietalkie/root": {
    "criteria": {
      "requirement": "2025-04-25 15:37:23 -0500"
    },
    "done": true
  },
  "walkietalkie:walkietalkie/iron_walkietalkie": {
    "criteria": {
      "requirement": "2025-04-25 15:37:23 -0500"
    },
    "done": true
  },
  "cold_sweat:extreme_temps": {
    "criteria": {
      "requirement": "2025-04-25 15:41:40 -0500"
    },
    "done": true
  },
  "spore:spore": {
    "criteria": {
      "pick_up_scanner": "2025-04-25 15:59:11 -0500"
    },
    "done": true
  },
  "minecraft:story/mine_stone": {
    "criteria": {
      "get_stone": "2025-04-25 16:31:15 -0500"
    },
    "done": true
  },
  "webdisplays:screen": {
    "criteria": {
      "has_screen": "2025-04-25 16:36:23 -0500"
    },
    "done": true
  },
  "minecraft:adventure/root": {
    "criteria": {
      "killed_something": "2025-04-25 17:23:12 -0500"
    },
    "done": true
  },
  "lootr:social": {
    "criteria": {
      "opened_barrel": "2025-04-25 17:13:38 -0500"
    },
    "done": false
  },
  "lootr:1barrel": {
    "criteria": {
      "opened_barrel": "2025-04-25 17:13:38 -0500"
    },
    "done": true
  },
  "DataVersion": 3465
}